validation_utils/__init__.py
validation_utils/validation.py
validation_utils-0.0.1.dist-info/METADATA
validation_utils-0.0.1.dist-info/WHEEL
validation_utils-0.0.1.dist-info/top_level.txt
validation_utils-0.0.1.dist-info/RECORD
