Metadata-Version: 2.1
Name: validation-utils
Version: 0.0.1
Summary: Validation utils library
Home-page: UNKNOWN
Author: Andrii Kovalov
Author-email: andy.kovv@gmail.com
License: UNKNOWN
Keywords: validation_utils
Platform: UNKNOWN
Classifier: Natural Language :: English
Classifier: Programming Language :: Python :: 2
Classifier: Programming Language :: Python :: 2.7
Classifier: Programming Language :: Python :: 3
Classifier: Programming Language :: Python :: 3.4
Classifier: Programming Language :: Python :: 3.5
Classifier: Programming Language :: Python :: 3.6
Classifier: Programming Language :: Python :: 3.7
Requires-Dist: atomicwrites (==1.3.0)
Requires-Dist: attrs (==19.1.0)
Requires-Dist: marshmallow (==2.19.2)
Requires-Dist: more-itertools (==7.0.0)
Requires-Dist: pluggy (==0.9.0)
Requires-Dist: py (==1.8.0)
Requires-Dist: pytest (==4.4.1)
Requires-Dist: six (==1.12.0)
